{
 "absolute_value": 0,
 "align_labels_right": 0,
 "creation": "2025-07-07 17:53:17.856191",
 "css": " div[document-status=\"draft\"]{\n     display:none;\n }\ntable,td {\n    border:1px solid black;\n    color:black;\n}\n table {\n     width:100%;\n     margin-bottom:10px;\n }",
 "custom_format": 0,
 "default_print_language": "en",
 "disabled": 0,
 "doc_type": "In-Principle Approval for CAPEX",
 "docstatus": 0,
 "doctype": "Print Format",
 "font_size": 14,
 "format_data": "[{\"fieldname\": \"print_heading_template\", \"fieldtype\": \"Custom HTML\", \"options\": \"<div></div>\"}, {\"fieldtype\": \"Section Break\", \"label\": \"\"}, {\"fieldtype\": \"Column Break\"}, {\"fieldname\": \"_custom_html\", \"print_hide\": 0, \"label\": \"Custom HTML\", \"fieldtype\": \"HTML\", \"options\": \"<br>\\n<div style=\\\"width: 100%; text-align: center;\\\">\\n    <div>\\n        <h3 style=\\\"margin: 0; font-size: 16px;\\\">IN-PRINCIPLE APPROVAL FOR CAPEX</h3>\\n    </div>\\n</div>\\n<br>\"}, {\"fieldtype\": \"Section Break\", \"label\": \"\"}, {\"fieldtype\": \"Column Break\"}, {\"fieldname\": \"_custom_html\", \"print_hide\": 0, \"label\": \"Custom HTML\", \"fieldtype\": \"HTML\", \"options\": \"<table style=\\\"width: 100%; border-collapse: collapse;\\\" border=\\\"1\\\">\\n    <tr>\\n        <th style = \\\"width:20%\\\">Department/section</th>\\n        <th style = \\\"width:20%\\\">Dept. Requisition No</th>\\n        <th style = \\\"width:20%\\\">Date of Requisition</th>\\n        <th style = \\\"width:20%\\\">Customer Order/WO Ref.</th>\\n        <th style = \\\"width:20%\\\">Capex Budget Code Ref.</th>\\n    </tr>\\n    <tr>\\n        <td style=\\\"width:20%; height: 80px;\\\">{{ doc.departmentsection or '' }}</td>\\n        <td style=\\\"width:20%\\\">{{ doc.department_requisition_no or '' }}</td>\\n        <td style=\\\"width:20%\\\">{{ doc.in_principle_request_date or '' }}</td>\\n        <td style=\\\"width:20%\\\">{{ doc.customer_orderwo_reference or '' }}</td>\\n        <td style=\\\"width:20%\\\">{{ doc.capex_budget_code_reference or '' }}</td>\\n    </tr>\\n</table>\\n<br>\"}, {\"fieldtype\": \"Section Break\", \"label\": \"\"}, {\"fieldtype\": \"Column Break\"}, {\"fieldname\": \"_custom_html\", \"print_hide\": 0, \"label\": \"Custom HTML\", \"fieldtype\": \"HTML\", \"options\": \"<table style=\\\"width: 100%; border-collapse: collapse; page-break-after:always;\\\" border=\\\"1\\\">\\n    <tr>\\n        <th style=\\\"width:5%; text-align: center;\\\">Sl.No</th>\\n        <th style=\\\"width:55%;text-align: center;\\\">Description of Capex</th>\\n        <th style=\\\"width:10%;text-align: center;\\\">Qty</th>\\n        <th style=\\\"width:10%;text-align: center;\\\">Unit</th>\\n        <th style=\\\"width:10%;text-align: center;\\\">Estimated Cost</th>\\n        <th style=\\\"width:10%; text-align: center;\\\">Date by which required</th>\\n    </tr>\\n    {% for i in doc.particulars %}\\n    <tr>\\n        <td style=\\\"text-align: center;\\\">{{ i.idx }}</td>\\n        <td style=\\\"text-align: left;\\\">{{ i.item }}: {{ i.description }}</td>\\n        <td style=\\\"text-align: center;\\\">{{ i.qty }}</td>\\n        <td style=\\\"text-align: center;\\\">{{ i.unit }}</td>\\n        <td style=\\\"text-align: center;\\\">{{ i.estimated_cost }}</td>\\n        <td style=\\\"text-align: center;\\\">{{ i.required_date }}</td>\\n    </tr>\\n    {% endfor %}\\n    <tr>\\n        <td style=\\\"text-align: left; height:100px;\\\" colspan=\\\"6\\\"><strong>Justification With Likely Financial Gain:</strong> : \\n    {{ doc.justification_with_likely_financial_gain or '' }}</td>\\n    </tr>\\n</table>\"}, {\"fieldtype\": \"Section Break\", \"label\": \"\"}, {\"fieldtype\": \"Column Break\"}, {\"fieldname\": \"_custom_html\", \"print_hide\": 0, \"label\": \"Custom HTML\", \"fieldtype\": \"HTML\", \"options\": \"<table style=\\\"width: 100%; border-collapse: collapse;\\\" border=\\\"1\\\">\\n\\n    <tr>\\n        <th style=\\\"width: 20%; text-align: center; vertical-align: middle;\\\">\\n            Indenter \\n        </th>\\n        <th style=\\\"width: 20%; text-align: center; vertical-align: middle;\\\">\\n            DM / AGM\\n        </th>\\n        <th style=\\\"width: 20%; text-align: center; vertical-align: middle;\\\">\\n            CS\\n        </th>\\n        <th style=\\\"width: 20%; text-align: center; vertical-align: middle;\\\">\\n            CFO\\n        </th>\\n        <th style=\\\"width: 20%; text-align: center; vertical-align: middle;\\\">\\n            GM (Ops)\\n        </th>\\n    </tr>\\n    <tr>\\n        <td style=\\\"width: 20%; text-align: center; vertical-align: middle;\\\">\\n            &nbsp; \\n        </td>\\n        <td style=\\\"width: 20%; text-align: center; vertical-align: middle;\\\">\\n            Comments/<br>Recommendations\\n        </td>\\n        <td style=\\\"width: 20%; text-align: center; vertical-align: middle;\\\">\\n            Comments/<br>Recommendations\\n        </td>\\n        <td style=\\\"width: 20%; text-align: center; vertical-align: middle;\\\">\\n            Comments/<br>Recommendations\\n        </td>\\n        <td style=\\\"width: 20%; text-align: center; vertical-align: middle;\\\">\\n            Comments/<br>Recommendations\\n        </td>\\n    </tr>\\n    <tr>\\n        <td style=\\\"width: 20%; height: 100px;\\\">\\n           &nbsp;  \\n        </td>\\n        <td style=\\\"width: 20%; text-align: center; vertical-align: middle;\\\">\\n            &nbsp;\\n        </td>\\n        <td style=\\\"width: 20%; text-align: center; vertical-align: middle;\\\">\\n            &nbsp;\\n        </td>\\n        <td style=\\\"width: 20%; text-align: center; vertical-align: middle;\\\">\\n            &nbsp;\\n        </td>\\n        <td style=\\\"width: 20%; text-align: center; vertical-align: middle;\\\">\\n            &nbsp;\\n        </td>\\n    </tr>\\n    <tr>\\n        <td style=\\\"width: 20%;\\\">\\n           (Name & <br>Signature <br>with date)  \\n        </td>\\n        <td style=\\\"width: 20%; text-align: center; vertical-align: middle;\\\">\\n            (Name & <br>Signature <br>with date)  \\n        </td>\\n        <td style=\\\"width: 20%; text-align: center; vertical-align: middle;\\\">\\n            (Name & <br>Signature <br>with date)  \\n        </td>\\n        <td style=\\\"width: 20%; text-align: center; vertical-align: middle;\\\">\\n            (Name & <br>Signature <br>with date)  \\n        </td>\\n        <td style=\\\"width: 20%; text-align: center; vertical-align: middle;\\\">\\n            (Name & <br>Signature <br>with date)  \\n        </td>\\n    </tr>\\n</table>\\n\"}]",
 "idx": 0,
 "line_breaks": 0,
 "margin_bottom": 15.0,
 "margin_left": 15.0,
 "margin_right": 15.0,
 "margin_top": 15.0,
 "modified": "2025-07-15 14:54:45.910694",
 "modified_by": "Administrator",
 "module": "A3 Procurement",
 "name": "In-Principle Approval for CAPEX",
 "owner": "Administrator",
 "page_number": "Hide",
 "pdf_generator": "wkhtmltopdf",
 "print_format_builder": 0,
 "print_format_builder_beta": 0,
 "print_format_type": "Jinja",
 "raw_printing": 0,
 "show_section_headings": 0,
 "standard": "Yes"
}