{
 "absolute_value": 0,
 "align_labels_right": 0,
 "creation": "2025-07-07 16:37:34.869323",
 "css": "table,td,th {\n    border:1px solid black;\n    color:black;\n}\n table {\n     width:100%;\n     margin-bottom:10px;\n }\n \n \n div[document-status=\"draft\"]{\n     display:none;\n }\n \n .print-format{\n    margin-top: 0;\n    margin-bottom: 0;\n}\n",
 "custom_format": 0,
 "default_print_language": "en",
 "disabled": 0,
 "doc_type": "Indent",
 "docstatus": 0,
 "doctype": "Print Format",
 "font_size": 14,
 "format_data": "[{\"fieldname\": \"print_heading_template\", \"fieldtype\": \"Custom HTML\", \"options\": \"<div></div>\"}, {\"fieldtype\": \"Section Break\", \"label\": \"\"}, {\"fieldtype\": \"Column Break\"}, {\"fieldname\": \"_custom_html\", \"print_hide\": 0, \"label\": \"Custom HTML\", \"fieldtype\": \"HTML\", \"options\": \"<h3 style =\\\"text-align:center\\\">PURCHASE INDENT</h3>\"}, {\"fieldname\": \"_custom_html\", \"print_hide\": 0, \"label\": \"Custom HTML\", \"fieldtype\": \"HTML\", \"options\": \"<table>\\n    <tr>\\n        <td style = \\\"width:20%\\\">Indent No</td>\\n        <td style = \\\"width:20%\\\">{{doc.name}}</td>\\n        <td style = \\\"width:20%\\\">Indent Date</td>\\n        <td style = \\\"width:20%\\\">{{doc.indent_date}}</td>\\n\\n    </tr>\\n    <tr>\\n        <td>Dept. Requisition No.</td>\\n        <td>{{doc.department_requisition_number}}</td>\\n        <td>requisition Date</td>\\n        <td>{{doc.date_of_requisition}}</td>\\n\\n    </tr>\\n    <tr>\\n        <td>Category</td>\\n        <td>{{doc.store_category}}</td>\\n        <td>Cost Range</td>\\n        <td>{{doc.cost_range}}</td>\\n\\n    </tr>\\n     <tr>\\n        <td>Ref:WO No</td>\\n        <td>{{doc.reference_wo_no}}</td>\\n        <td>C-Form Applicable N/A</td>\\n        <td>{{doc.c_form_applicable}}</td>\\n\\n    </tr>\\n</table>\"}, {\"fieldtype\": \"Section Break\", \"label\": \"\"}, {\"fieldtype\": \"Column Break\"}, {\"fieldname\": \"_custom_html\", \"print_hide\": 0, \"label\": \"Custom HTML\", \"fieldtype\": \"HTML\", \"options\": \"<h5><b>CAPEX Approval</b></h5>\\n<table>\\n    <tr>\\n        <td></td>\\n        <td></td>\\n        <td></td>\\n        <td></td>\\n    </tr>\\n</table>\"}, {\"fieldtype\": \"Section Break\", \"label\": \"\"}, {\"fieldtype\": \"Column Break\"}, {\"fieldname\": \"_custom_html\", \"print_hide\": 0, \"label\": \"Custom HTML\", \"fieldtype\": \"HTML\", \"options\": \"<table>\\n    <tr>\\n        <th>Sl.No</td>\\n        <th>Item Code</td>\\n        <th>Description</td>\\n        <th>Qty</td>\\n        <th>Unit</td>\\n        <th>Date by which required</td>\\n    </tr>\\n    {% for i in doc.items %}\\n    <tr>\\n        <td>{{i.idx}}</td>\\n        <td>{{i.item}}</td>\\n        <td>{{i.description}}</td>\\n        <td>{{i.qty}}</td>\\n        <td>{{i.unit}}</td>\\n        <td>{{i.required_date}}</td>\\n    </tr>\\n    {% endfor %}\\n</table>\"}, {\"fieldtype\": \"Section Break\", \"label\": \"\"}, {\"fieldtype\": \"Column Break\"}, {\"fieldname\": \"_custom_html\", \"print_hide\": 0, \"label\": \"Custom HTML\", \"fieldtype\": \"HTML\", \"options\": \"<table>\\n    <tr>\\n        <td colspan = \\\"3\\\"><b>Justification</b><br>\\n         {{doc.justification}}</td>\\n    </tr>\\n    <tr>\\n        <th colspan = \\\"3\\\">Source of supply Known to Indentor</th>\\n    </tr>\\n    <tr>\\n        <td>1.{{doc.source_1}}</td>\\n        <td>2.{{doc.source_2}}</td>\\n        <td>3.{{doc.source_3}}</td>\\n    </tr>\\n</table>\"}, {\"fieldtype\": \"Section Break\", \"label\": \"\"}, {\"fieldtype\": \"Column Break\"}, {\"fieldname\": \"_custom_html\", \"print_hide\": 0, \"label\": \"Custom HTML\", \"fieldtype\": \"HTML\", \"options\": \"<table>\\n    <tr>\\n        <th colspan= \\\"2\\\">HISTORY CARD(To be filled by indentor)</th>\\n    </tr>\\n    <tr>\\n        <td style= \\\"width:50%\\\">Specification as per last Indent</td>\\n        <td>{{doc.specification_as_per_last_indent}}</td>\\n    </tr>\\n    <tr>\\n        <td>Month of last procurement</td>\\n        <td>{{doc.month_of_last_procurement}}</td>\\n    </tr>\\n    <tr>\\n        <td>Average consumption(Monthly/Yearly)</td>\\n        <td>{{doc.average_consumption}}</td>\\n    </tr>\\n    <tr>\\n        <td>Requirement planned for</td>\\n        <td>{{doc.requirement_planned_for}}</td>\\n    </tr>\\n    \\n</table>\\n\\n<table>\\n    <tr>\\n        <th colspan = \\\"3\\\">\\n            <b>Check List:</b>Indicate whether the following requirements are provided\\n        </th>\\n    </tr>\\n         <tr>\\n            <td>(1) Specifications</td>\\n            <td><input type=\\\"checkbox\\\" ></td>\\n            <td><input type=\\\"checkbox\\\" ></td>\\n        </tr>\\n        <tr>\\n            <td>(2) Quality requirements</td>\\n            <td><input type=\\\"checkbox\\\" {% if doc.quality_requirements_yes %}checked{% endif %}></td>\\n            <td><input type=\\\"checkbox\\\" {% if doc.quality_requirements_no %}checked{% endif %}></td>\\n        </tr>\\n        <tr>\\n            <td>(3) Justification</td>\\n            <td><input type=\\\"checkbox\\\" ></td>\\n            <td><input type=\\\"checkbox\\\" ></td>\\n        </tr>\\n        <tr>\\n            <td>(4) Special Instructions</td>\\n            <td><input type=\\\"checkbox\\\" {% if doc.special_instructions_yes %}checked{% endif %}></td>\\n            <td><input type=\\\"checkbox\\\" {% if doc.special_instructions_no %}checked{% endif %}></td>\\n        </tr>\\n        <tr>\\n            <td>(5) Cost Estimate in sealed envelope</td>\\n            <td><input type=\\\"checkbox\\\" {% if doc.cost_estimate_yes %}checked{% endif %}></td>\\n            <td><input type=\\\"checkbox\\\" {% if doc.cost_estimate_no %}checked{% endif %}></td>\\n        </tr>\\n</table>\"}, {\"fieldtype\": \"Section Break\", \"label\": \"\"}, {\"fieldtype\": \"Column Break\"}, {\"fieldname\": \"_custom_html\", \"print_hide\": 0, \"label\": \"Custom HTML\", \"fieldtype\": \"HTML\", \"options\": \"<table>\\n    <tr>\\n        <td style =\\\"border:None\\\">Indentor:</td>\\n        <td style =\\\"border:None\\\">Recommended by:</td>\\n        <td style =\\\"border:None\\\">Reviewd by:</td>\\n    </tr>\\n</table>\"}, {\"fieldtype\": \"Section Break\", \"label\": \"\"}, {\"fieldtype\": \"Column Break\"}, {\"fieldname\": \"_custom_html\", \"print_hide\": 0, \"label\": \"Custom HTML\", \"fieldtype\": \"HTML\", \"options\": \"<h5><b>INDENT REVIEW INFORMATION (To be filled by CMM)</b></h5>\\n\\n<table style=\\\"width: 100%;\\\">\\n    <thead>\\n        <tr>\\n            <th>Indentor specification (in full)</th>\\n            <th>Stock position in stores</th>\\n            <th>Date of last procurement</th>\\n            <th>Last procurement rate</th>\\n            <th>Current procurement rate</th>\\n        </tr>\\n    </thead>\\n    <tbody>\\n        <tr>\\n            <td>{{ doc.indentor_specification }}</td>\\n            <td>{{ doc.stock_position_in_stores  }}</td>\\n            <td>{{ doc.date_of_last_procurement}}</td>\\n            <td>{{ doc.last_procurement_rate }}</td>\\n            <td>{{ doc.current_procurement_rate }}</td>\\n        </tr>\\n    </tbody>\\n</table>\\n\\n<br>\\n\\n<table  style=\\\"width: 100%;\\\">\\n        <tr>\\n            <th colspan=\\\"2\\\">Probable suppliers</th>\\n        </tr>\\n        <tr>\\n            <td>1. {{ doc.supplier_1 }}</td>\\n        </tr>\\n         <tr>\\n            <td>2. {{ doc.supplier_2 }}</td>\\n        </tr>\\n         <tr>\\n            <td>3. {{ doc.supplier_3 }}</td>\\n        </tr>\\n</table>\\n\\n<br><br>\\n\\n<table style=\\\"width: 100%;\\\">\\n    <tr>\\n        <td><b>Prepared by:</b></td>\\n        <td><b>Checked by:</b><br>S/AE/E(DM/CMM)</td>\\n        <td><b>Verified by:</b><br>M/SM/DGM(CMM)</td>\\n    </tr>\\n</table>\\n\\n<br>\\n\\n<p style=\\\"font-size: 11px;\\\"><i>(If approved, tendering action to be initiated by CMM)</i></p>\\n<p style=\\\"font-size: 11px;\\\"><b>General Manager</b></p>\\n\"}]",
 "idx": 0,
 "line_breaks": 0,
 "margin_bottom": 15.0,
 "margin_left": 15.0,
 "margin_right": 15.0,
 "margin_top": 15.0,
 "modified": "2025-07-14 13:16:39.836938",
 "modified_by": "Administrator",
 "module": "A3 Procurement",
 "name": "Indent",
 "owner": "Administrator",
 "page_number": "Hide",
 "pdf_generator": "wkhtmltopdf",
 "print_format_builder": 0,
 "print_format_builder_beta": 0,
 "print_format_type": "Jinja",
 "raw_printing": 0,
 "show_section_headings": 0,
 "standard": "Yes"
}